{
    "page_num": 290,
    "min_max": {
        "max_row": {
            "value": 73,
            "row": "had seen those awful women growing into reality through the whirling mist"
        },
        "min_row": {
            "value": 3,
            "row": "is."
        }
    },
    "most_common_words": [
        [
            "which",
            636
        ],
        [
            "there",
            508
        ],
        [
            "could",
            458
        ],
        [
            "shall",
            410
        ],
        [
            "would",
            408
        ]
    ]
}